ha_tiny/__init__.py
ha_tiny/const.py
ha_tiny/extras.py
ha_tiny/version.py
ha_tiny-2024.8.2.dist-info/LICENSE
ha_tiny-2024.8.2.dist-info/METADATA
ha_tiny-2024.8.2.dist-info/WHEEL
ha_tiny-2024.8.2.dist-info/top_level.txt
ha_tiny-2024.8.2.dist-info/RECORD
