Metadata-Version: 2.1
Name: ha_tiny
Version: 2024.8.2
Summary: python module for rpi-home
Author-email: Bretton Wade <bretton.wade@irdev.us>
Maintainer-email: Bretton Wade <bretton.wade@irdev.us>
License: MIT License
Project-URL: Homepage, https://github.com/brettonw/rpi_home
Keywords: raspberry pi,home assistant
Classifier: Programming Language :: Python
Classifier: Programming Language :: Python :: 3
Requires-Python: >=3.9
License-File: LICENSE
Provides-Extra: dev
Requires-Dist: pytest; extra == "dev"
